pynteracta/__init__.py
pynteracta/__main__.py
pynteracta/api.py
pynteracta/cli/__init__.py
pynteracta/cli/commands.py
pynteracta/cli/users.py
pynteracta/cli/utils.py
pynteracta/constants.py
pynteracta/core.py
pynteracta/decorators.py
pynteracta/enums.py
pynteracta/exceptions.py
pynteracta/models.py
pynteracta/schemas/__init__.py
pynteracta/schemas/core.py
pynteracta/schemas/models.py
pynteracta/schemas/requests.py
pynteracta/schemas/responses.py
pynteracta/settings.py
pynteracta/urls.py
pynteracta/utils/__init__.py
pynteracta/utils/consts.py
pynteracta/utils/models.py
pynteracta/utils/stats.py
pynteracta-0.4.30.dist-info/LICENSE
pynteracta-0.4.30.dist-info/METADATA
pynteracta-0.4.30.dist-info/WHEEL
pynteracta-0.4.30.dist-info/entry_points.txt
pynteracta-0.4.30.dist-info/RECORD
