Metadata-Version: 2.1
Name: pynteracta
Version: 0.4.30
Summary: A wrapper for Interacta API
Home-page: https://github.com/simodalla/pynteracta
License: BSD-3-Clause
Author: Simone Dalla
Author-email: simodalla@gmail.com
Requires-Python: >=3.12
Classifier: Development Status :: 5 - Production/Stable
Classifier: Environment :: Console
Classifier: Environment :: MacOS X
Classifier: Framework :: Pydantic
Classifier: Framework :: Pydantic :: 2
Classifier: Intended Audience :: Developers
Classifier: Intended Audience :: Information Technology
Classifier: Intended Audience :: System Administrators
Classifier: License :: OSI Approved :: BSD License
Classifier: License :: OSI Approved :: MIT License
Classifier: Operating System :: POSIX :: Linux
Classifier: Operating System :: Unix
Classifier: Programming Language :: Python
Classifier: Programming Language :: Python :: 3
Classifier: Programming Language :: Python :: 3.12
Classifier: Programming Language :: Python :: 3.13
Classifier: Programming Language :: Python :: 3 :: Only
Classifier: Programming Language :: Python :: 3.10
Classifier: Programming Language :: Python :: 3.11
Classifier: Topic :: Internet
Classifier: Topic :: Software Development :: Libraries :: Python Modules
Requires-Dist: pydantic-settings (>=2.0.0,<3.0.0)
Requires-Dist: pydantic-settings-toml (>=0.2.0,<0.3.0)
Requires-Dist: pydantic[email] (>=2.3.0,<3.0.0)
Requires-Dist: pyjwt[crypto] (>=2.6.0,<3.0.0)
Requires-Dist: requests (>=2.28.1,<3.0.0)
Requires-Dist: typer (>=0.15.2,<0.16.0)
Project-URL: Repository, https://github.com/simodalla/pynteracta
